saf/__init__.py
saf/manager.py
saf/models.py
saf/pipeline.py
saf/plugins.py
saf/py.typed
saf/version.py
saf/collect/__init__.py
saf/collect/beacons.py
saf/collect/file.py
saf/collect/salt_exec.py
saf/collect/test.py
saf/forward/__init__.py
saf/forward/disk.py
saf/forward/noop.py
saf/forward/test.py
saf/process/__init__.py
saf/process/jupyter_notebook.py
saf/process/regex_mask.py
saf/process/shannon_mask.py
saf/process/test.py
saf/saltext/__init__.py
saf/saltext/engines/__init__.py
saf/saltext/engines/analytics.py
saf/utils/__init__.py
saf/utils/dt.py
saf/utils/eventbus.py
salt_analytics_framework-0.5.0.dist-info/LICENSE
salt_analytics_framework-0.5.0.dist-info/METADATA
salt_analytics_framework-0.5.0.dist-info/NOTICE
salt_analytics_framework-0.5.0.dist-info/WHEEL
salt_analytics_framework-0.5.0.dist-info/entry_points.txt
salt_analytics_framework-0.5.0.dist-info/top_level.txt
salt_analytics_framework-0.5.0.dist-info/RECORD
