Metadata-Version: 2.1
Name: salt-analytics-framework
Version: 0.5.0
Summary: Salt Analytics Framework
Home-page: https://github.com/saltstack/salt-analytics-framework
Author: Pedro Algarvio
Author-email: palgarvio@vmware.com
License: Apache Software License
Project-URL: Source, https://github.com/saltstack/salt-analytics-framework
Project-URL: Tracker, https://github.com/saltstack/salt-analytics-framework/issues
Keywords: salt-extension
Platform: any
Classifier: Programming Language :: Python
Classifier: Programming Language :: Cython
Classifier: Programming Language :: Python :: 3
Classifier: Programming Language :: Python :: 3 :: Only
Classifier: Programming Language :: Python :: 3.7
Classifier: Programming Language :: Python :: 3.8
Classifier: Programming Language :: Python :: 3.9
Classifier: Development Status :: 4 - Beta
Classifier: Intended Audience :: Developers
Classifier: License :: OSI Approved :: Apache Software License
Requires-Python: >=3.7
License-File: LICENSE
License-File: NOTICE
Requires-Dist: aiofiles
Requires-Dist: aiorun
Requires-Dist: aiostream
Requires-Dist: backoff
Requires-Dist: drain3
Requires-Dist: psutil
Requires-Dist: pydantic (>=1.8.2)
Requires-Dist: salt (>=3005)
Requires-Dist: importlib-metadata (<5.0.0,>=3.4.0) ; python_version < "3.8"
Requires-Dist: typing-extensions ; python_version < "3.9.2"
Provides-Extra: build
Requires-Dist: twine ; extra == 'build'
Requires-Dist: build (>=0.7.0) ; extra == 'build'
Provides-Extra: changelog
Requires-Dist: towncrier (==21.9.0rc1) ; extra == 'changelog'
Provides-Extra: dev
Requires-Dist: nox ; extra == 'dev'
Requires-Dist: pre-commit ; extra == 'dev'
Requires-Dist: mypy (>=0.910) ; extra == 'dev'
Requires-Dist: types-attrs ; extra == 'dev'
Requires-Dist: types-setuptools ; extra == 'dev'
Requires-Dist: pylint (==2.12.2) ; extra == 'dev'
Requires-Dist: astroid (==2.9.3) ; extra == 'dev'
Requires-Dist: pylint-pydantic ; extra == 'dev'
Requires-Dist: pyenchant ; extra == 'dev'
Requires-Dist: flake8 ; extra == 'dev'
Requires-Dist: flake8-mypy-fork ; extra == 'dev'
Requires-Dist: flake8-docstrings ; extra == 'dev'
Requires-Dist: flake8-typing-imports ; extra == 'dev'
Provides-Extra: docs
Requires-Dist: furo ; extra == 'docs'
Requires-Dist: sphinx ; extra == 'docs'
Requires-Dist: sphinx-copybutton ; extra == 'docs'
Requires-Dist: sphinx-prompt ; extra == 'docs'
Requires-Dist: sphinxcontrib-spelling ; extra == 'docs'
Requires-Dist: sphinxcontrib-towncrier (>=0.2.1a0) ; extra == 'docs'
Requires-Dist: autodoc-pydantic ; extra == 'docs'
Provides-Extra: docsauto
Requires-Dist: sphinx-autobuild ; extra == 'docsauto'
Provides-Extra: tests
Requires-Dist: pytest (>=6.0.0) ; extra == 'tests'
Requires-Dist: pytest-salt-factories (==1.0.0rc21) ; extra == 'tests'
Requires-Dist: pytest-asyncio ; extra == 'tests'
